dspin/__init__.py
dspin/annotate.py
dspin/compute.py
dspin/dspin.py
dspin/gpt.py
dspin/metadata_drug.py
dspin/plot.py
dspin-1.1.0.dist-info/LICENSE
dspin-1.1.0.dist-info/METADATA
dspin-1.1.0.dist-info/WHEEL
dspin-1.1.0.dist-info/top_level.txt
dspin-1.1.0.dist-info/RECORD
