Metadata-Version: 2.1
Name: dspin
Version: 1.1.0
Summary: Regulatory network models from single-cell perturbation profiling
Home-page: https://github.com/JialongJiang/DSPIN
Author: Jialong Jiang
Author-email: jiangjl@caltech.edu
License: Apache-2.0 license
Keywords: network inference,single cell,transcriptomics
Classifier: Development Status :: 4 - Beta
Classifier: Intended Audience :: Science/Research
Classifier: Operating System :: OS Independent
Classifier: Programming Language :: Python :: 3
Classifier: Programming Language :: Python :: 3.9
Classifier: License :: OSI Approved :: Apache Software License
Classifier: Topic :: Scientific/Engineering :: Bio-Informatics
Classifier: Topic :: Scientific/Engineering :: Information Analysis
Classifier: Topic :: Scientific/Engineering :: Physics
Requires-Python: >=3.6
License-File: LICENSE
Requires-Dist: anndata
Requires-Dist: matplotlib
Requires-Dist: scanpy
Requires-Dist: tqdm
Requires-Dist: igraph
Requires-Dist: leidenalg
